pyfiat/__init__.py
pyfiat/api.py
pyfiat/brands.py
pyfiat/client.py
pyfiat/command.py
python_fiat_api_blueion-0.2.0.dist-info/METADATA
python_fiat_api_blueion-0.2.0.dist-info/WHEEL
python_fiat_api_blueion-0.2.0.dist-info/top_level.txt
python_fiat_api_blueion-0.2.0.dist-info/RECORD
